{"stat.useItem.minecraft.bow":23,"stat.walkOneCm":198910,"stat.playerKills":11,"stat.leaveGame":6,"stat.useItem.minecraft.cobblestone":78,"stat.useItem.minecraft.lava_bucket":3,"stat.useItem.minecraft.diamond_sword":145,"stat.useItem.minecraft.potion":13,"stat.swimOneCm":4290,"stat.jump":41,"stat.fallOneCm":24028,"stat.useItem.minecraft.planks":4,"stat.crouchOneCm":1873,"stat.sprintOneCm":115333,"achievement.exploreAllBiomes":{"value":0,"progress":["Jungle","Plains"]},"stat.useItem.minecraft.water_bucket":3,"achievement.openInventory":19,"stat.useItem.minecraft.iron_sword":6,"stat.useItem.minecraft.flint_and_steel":1,"stat.damageTaken":2610,"stat.useItem.minecraft.bucket":2,"stat.useItem.minecraft.golden_apple":11,"stat.flyOneCm":115448,"stat.deaths":3,"stat.useItem.minecraft.ender_pearl":6,"stat.drop":2,"stat.playOneMinute":20603,"stat.useItem.minecraft.cooked_beef":1,"stat.useItem.minecraft.stone_sword":22,"stat.damageDealt":19649,"stat.timeSinceDeath":598,"stat.useItem.minecraft.fishing_rod":87}