{"stat.breakItem.minecraft.flint_and_steel":3,"stat.useItem.minecraft.bow":201,"stat.walkOneCm":1158138,"stat.playerKills":25,"stat.leaveGame":8,"stat.mineBlock.minecraft.cobblestone":2,"stat.useItem.minecraft.cobblestone":480,"stat.useItem.minecraft.golden_carrot":5,"stat.useItem.minecraft.lava_bucket":21,"stat.useItem.minecraft.diamond_sword":802,"stat.useItem.minecraft.potion":65,"stat.jump":257,"stat.swimOneCm":9463,"stat.fallOneCm":102137,"stat.useItem.minecraft.planks":77,"stat.climbOneCm":264,"stat.crouchOneCm":1321,"stat.sprintOneCm":656436,"achievement.exploreAllBiomes":{"value":0,"progress":["Jungle","Plains"]},"stat.breakItem.minecraft.diamond_helmet":7,"stat.useItem.minecraft.water_bucket":17,"achievement.openInventory":114,"stat.useItem.minecraft.iron_sword":5,"stat.useItem.minecraft.flint_and_steel":28,"stat.damageTaken":22731,"stat.useItem.minecraft.diamond_pickaxe":2,"stat.useItem.minecraft.bucket":30,"stat.useItem.minecraft.golden_apple":105,"stat.flyOneCm":718224,"stat.deaths":18,"stat.useItem.minecraft.ender_pearl":6,"stat.drop":1,"stat.playOneMinute":152976,"stat.useItem.minecraft.cooked_beef":8,"stat.useItem.minecraft.stone_sword":126,"stat.damageDealt":174232,"stat.timeSinceDeath":16615,"stat.useItem.minecraft.fishing_rod":726}