{"stat.useItem.minecraft.bow":52,"stat.walkOneCm":494980,"stat.playerKills":17,"stat.leaveGame":5,"stat.useItem.minecraft.cobblestone":1,"stat.useItem.minecraft.lava_bucket":4,"stat.useItem.minecraft.diamond_sword":307,"stat.useItem.minecraft.potion":70,"stat.jump":78,"stat.swimOneCm":1614,"stat.fallOneCm":38322,"stat.crouchOneCm":1603,"stat.sprintOneCm":296189,"achievement.exploreAllBiomes":{"value":0,"progress":["Jungle","Plains"]},"stat.breakItem.minecraft.diamond_helmet":1,"stat.useItem.minecraft.water_bucket":3,"achievement.openInventory":61,"stat.useItem.minecraft.iron_sword":4,"stat.useItem.minecraft.flint_and_steel":7,"stat.damageTaken":10967,"stat.useItem.minecraft.bucket":2,"stat.useItem.minecraft.golden_apple":31,"stat.flyOneCm":330082,"stat.deaths":16,"stat.useItem.minecraft.ender_pearl":11,"stat.drop":1,"stat.playOneMinute":49192,"stat.useItem.minecraft.cooked_beef":5,"stat.useItem.minecraft.stone_sword":149,"stat.damageDealt":54829,"stat.timeSinceDeath":1907,"stat.useItem.minecraft.fishing_rod":279}