{"stat.useItem.minecraft.bow":12,"stat.walkOneCm":113963,"stat.playerKills":1,"achievement.openInventory":9,"stat.leaveGame":3,"stat.useItem.minecraft.flint_and_steel":2,"stat.damageTaken":3356,"stat.useItem.minecraft.diamond_sword":64,"stat.useItem.minecraft.potion":26,"stat.useItem.minecraft.golden_apple":8,"stat.flyOneCm":96154,"stat.deaths":4,"stat.useItem.minecraft.ender_pearl":10,"stat.jump":23,"stat.swimOneCm":296,"stat.playOneMinute":11369,"stat.fallOneCm":6453,"stat.useItem.minecraft.cooked_beef":2,"stat.useItem.minecraft.stone_sword":24,"stat.damageDealt":22028,"stat.crouchOneCm":677,"stat.timeSinceDeath":22,"stat.sprintOneCm":62704,"achievement.exploreAllBiomes":{"value":0,"progress":["Jungle","Plains"]},"stat.useItem.minecraft.fishing_rod":35}